Workbook

Sheet Supuestos
A1: CREE EN TI: DESPIERTA TU PODER INTERIOR
A2: Supuestos del modelo financiero — Modificar en azul
A4: INGRESOS
A5: Precio entrada (IVA incluido) | B5: 78
A6: IVA aplicable | B6: 0.21
A7: Precio neto por entrada (sin IVA) | B7: =B5/(1+B6) -> 64.46281
A9: COSTOS VARIABLES (por asistente)
A10: Comisión plataforma ticketing (% sobre precio bruto) | B10: 0.065
A11: Fee fijo por transacción (plataforma) | B11: 0.99
A13: COSTOS FIJOS (por evento)
A14: Renta del local | B14: 400
A15: Seguro responsabilidad civil | B15: 150
A16: Materiales e impresos | B16: 60
A17: Marketing y publicidad digital | B17: 250
A18: Gestión administrativa (gestoría, % evento) | B18: 120
A19: Producción y logística | B19: 80
A21: DISTRIBUCIÓN DE BENEFICIO NETO
A22: Porción Mariana Verner (%) | B22: 0.4
A23: Porción co-ponente (%) | B23: 0.4
A24: Porción empresa ∞ SL (%) | B24: 0.2
A26: ★ Celdas en AZUL = inputs modificables. Negro = fórmulas. No modificar celdas negras.

Sheet Corrida Financiera
A1: CREE EN TI: DESPIERTA TU PODER INTERIOR — CORRIDA FINANCIERA POR EVENTO
A2: ∞ SL · Madrid, España · Escenarios: 50 / 70 / 100 / 150 asistentes por evento
A4: Concepto | B4: Notas | C4: 50 asistentes | D4: 70 asistentes | E4: 100 asistentes | F4: 150 asistentes
A5: ASISTENTES
A6: Asistentes por evento | B6: Input modificable | C6: 50 | D6: 70 | E6: 100 | F6: 150
A7: Ocupación del aforo estimado | B7: Ref.: capacidad ~150 plazas | C7: =C6/150 -> 0.33333333 | D7: =D6/150 -> 0.46666667 | E7: =E6/150 -> 0.66666667 | F7: =F6/150 -> 1
A9: INGRESOS BRUTOS
A10: Ingresos brutos totales (IVA incl.) | B10: Asistentes × precio bruto | C10: =Supuestos!$B$5*C6 -> 3900 | D10: =Supuestos!$B$5*D6 -> 5460 | E10: =Supuestos!$B$5*E6 -> 7800 | F10: =Supuestos!$B$5*F6 -> 11700
A11: IVA repercutido (a Hacienda) | B11: 21% sobre precio neto | C11: =(C10-C10/(1+Supuestos!$B$6)) -> 676.8595 | D11: =(D10-D10/(1+Supuestos!$B$6)) -> 947.60331 | E11: =(E10-E10/(1+Supuestos!$B$6)) -> 1353.719 | F11: =(F10-F10/(1+Supuestos!$B$6)) -> 2030.5785
A12: Ingresos netos (sin IVA) | B12: Base imponible real | C12: =C10-C11 -> 3223.1405 | D12: =D10-D11 -> 4512.3967 | E12: =E10-E11 -> 6446.281 | F12: =F10-F11 -> 9669.4215
A14: COSTOS VARIABLES
A15: Comisión plataforma ticketing | B15: 6.5% + 0.99€/transacción | C15: =(Supuestos!$B$10*Supuestos!$B$5+Supuestos!$B$11)*C6 -> 303 | D15: =(Supuestos!$B$10*Supuestos!$B$5+Supuestos!$B$11)*D6 -> 424.2 | E15: =(Supuestos!$B$10*Supuestos!$B$5+Supuestos!$B$11)*E6 -> 606 | F15: =(Supuestos!$B$10*Supuestos!$B$5+Supuestos!$B$11)*F6 -> 909
A17: COSTOS FIJOS
A18: Renta del local | B18: Fuente: estimación Madrid | C18: =Supuestos!$B$14 -> 400 | D18: =Supuestos!$B$14 -> 400 | E18: =Supuestos!$B$14 -> 400 | F18: =Supuestos!$B$14 -> 400
A19: Seguro responsabilidad civil | B19: Por evento | C19: =Supuestos!$B$15 -> 150 | D19: =Supuestos!$B$15 -> 150 | E19: =Supuestos!$B$15 -> 150 | F19: =Supuestos!$B$15 -> 150
A20: Materiales e impresos | B20: Impresiones, carpetas, etc. | C20: =Supuestos!$B$16 -> 60 | D20: =Supuestos!$B$16 -> 60 | E20: =Supuestos!$B$16 -> 60 | F20: =Supuestos!$B$16 -> 60
A21: Marketing y publicidad | B21: Redes, ads, diseño | C21: =Supuestos!$B$17 -> 250 | D21: =Supuestos!$B$17 -> 250 | E21: =Supuestos!$B$17 -> 250 | F21: =Supuestos!$B$17 -> 250
A22: Gestión administrativa | B22: Gestoría, trámites | C22: =Supuestos!$B$18 -> 120 | D22: =Supuestos!$B$18 -> 120 | E22: =Supuestos!$B$18 -> 120 | F22: =Supuestos!$B$18 -> 120
A23: Producción y logística | B23: Sonido, proyección, agua | C23: =Supuestos!$B$19 -> 80 | D23: =Supuestos!$B$19 -> 80 | E23: =Supuestos!$B$19 -> 80 | F23: =Supuestos!$B$19 -> 80
A24: Total costos fijos | C24: =SUM(C18:C23) -> 1060 | D24: =SUM(D18:D23) -> 1060 | E24: =SUM(E18:E23) -> 1060 | F24: =SUM(F18:F23) -> 1060
A26: RESULTADOS
A27: Total costos (variables + fijos) | C27: =C15+C24 -> 1363 | D27: =D15+D24 -> 1484.2 | E27: =E15+E24 -> 1666 | F27: =F15+F24 -> 1969
A28: EBITDA (beneficio antes impuestos) | B28: Ingreso neto − todos costos | C28: =C12-C27 -> 1860.1405 | D28: =D12-D27 -> 3028.1967 | E28: =E12-E27 -> 4780.281 | F28: =F12-F27 -> 7700.4215
A29: Margen EBITDA (%) | B29: EBITDA / Ingresos netos | C29: =IF(C12<>0,C28/C12,0) -> 0.57712051 | D29: =IF(D12<>0,D28/D12,0) -> 0.67108388 | E29: =IF(E12<>0,E28/E12,0) -> 0.74155641 | F29: =IF(F12<>0,F28/F12,0) -> 0.79636838
A31: Punto de equilibrio (asistentes) | B31: Mín. para cubrir costos | C31: =CEILING(Supuestos!$B$18+Supuestos!$B$19+Supuestos!$B$14+Supuestos!$B$15+Supuestos!$B$16+Supuestos!$B$17,1)/(Supuestos!$B$7-(Supuestos!$B$10*Supuestos!$B$5+Supuestos!$B$11)) -> 18.149812 | D31: =CEILING(Supuestos!$B$18+Supuestos!$B$19+Supuestos!$B$14+Supuestos!$B$15+Supuestos!$B$16+Supuestos!$B$17,1)/(Supuestos!$B$7-(Supuestos!$B$10*Supuestos!$B$5+Supuestos!$B$11)) -> 18.149812 | E31: =CEILING(Supuestos!$B$18+Supuestos!$B$19+Supuestos!$B$14+Supuestos!$B$15+Supuestos!$B$16+Supuestos!$B$17,1)/(Supuestos!$B$7-(Supuestos!$B$10*Supuestos!$B$5+Supuestos!$B$11)) -> 18.149812 | F31: =CEILING(Supuestos!$B$18+Supuestos!$B$19+Supuestos!$B$14+Supuestos!$B$15+Supuestos!$B$16+Supuestos!$B$17,1)/(Supuestos!$B$7-(Supuestos!$B$10*Supuestos!$B$5+Supuestos!$B$11)) -> 18.149812
A33: DISTRIBUCIÓN DEL BENEFICIO
A34: Mariana Verner (40%) | B34: Sobre EBITDA positivo | C34: =MAX(0,C28*Supuestos!$B$22) -> 744.0562 | D34: =MAX(0,D28*Supuestos!$B$22) -> 1211.2787 | E34: =MAX(0,E28*Supuestos!$B$22) -> 1912.1124 | F34: =MAX(0,F28*Supuestos!$B$22) -> 3080.1686
A35: Co-ponente (40%) | B35: Sobre EBITDA positivo | C35: =MAX(0,C28*Supuestos!$B$23) -> 744.0562 | D35: =MAX(0,D28*Supuestos!$B$23) -> 1211.2787 | E35: =MAX(0,E28*Supuestos!$B$23) -> 1912.1124 | F35: =MAX(0,F28*Supuestos!$B$23) -> 3080.1686
A36: ∞ SL — reserva empresa (20%) | B36: Sobre EBITDA positivo | C36: =MAX(0,C28*Supuestos!$B$24) -> 372.0281 | D36: =MAX(0,D28*Supuestos!$B$24) -> 605.63934 | E36: =MAX(0,E28*Supuestos!$B$24) -> 956.0562 | F36: =MAX(0,F28*Supuestos!$B$24) -> 1540.0843
A38: ACUMULADO 3 EVENTOS MADRID
A39: EBITDA total (3 eventos mismo escenario) | B39: × 3 fechas Madrid | C39: =C28*3 -> 5580.4215 | D39: =D28*3 -> 9084.5901 | E39: =E28*3 -> 14340.843 | F39: =F28*3 -> 23101.264
A40: Distribución Mariana Verner (3 eventos) | C40: =C39*Supuestos!$B$22 -> 2232.1686 | D40: =D39*Supuestos!$B$22 -> 3633.836 | E40: =E39*Supuestos!$B$22 -> 5736.3372 | F40: =F39*Supuestos!$B$22 -> 9240.5058
A41: Distribución co-ponente (3 eventos)
A42: Reserva ∞ SL (3 eventos) | C42: =C39*Supuestos!$B$24 -> 1116.0843 | D42: =D39*Supuestos!$B$24 -> 1816.918 | E42: =E39*Supuestos!$B$24 -> 2868.1686 | F42: =F39*Supuestos!$B$24 -> 4620.2529

Sheet Línea de Tiempo
A1: LÍNEA DE TIEMPO — CREE EN TI: DESPIERTA TU PODER INTERIOR
A2: ∞ SL · Gira España 2025 → América Latina 2026 → España 2027
A4: Fecha | B4: Hito | C4: Ciudad | D4: Acción principal | E4: Estado
A5: Mayo 2025 | B5: Diagnóstico y reactivación SL | C5: Madrid | D5: Modelo 036 ante AEAT · CIF activo | E5: ⏳ Pendiente
A6: Junio 2025 | B6: Contratos y documentación legal | C6: Madrid | D6: Contrato ponentes · Seguro · RGPD | E6: ⏳ Pendiente
A7: Junio 2025 | B7: Configuración fiscal y bancaria | C7: Madrid | D7: IVA definido · Cuenta SL · Plataforma ticketing | E7: ⏳ Pendiente
A8: Agosto 2025 | B8: Apertura venta de entradas | C8: Online | D8: Landing live · Venta activa · 20€ reserva | E8: ⏳ Pendiente
A9: 24 Sep 2025 | B9: EVENTO 1 — Primer taller | C9: Madrid 🇪🇸 | D9: Cree en ti: despierta tu poder interior | E9: 🎯 Objetivo
A10: 26 Oct 2025 | B10: EVENTO 2 — Segunda edición | C10: Madrid 🇪🇸 | D10: Cree en ti: despierta tu poder interior | E10: 🎯 Objetivo
A11: 26 Nov 2025 | B11: EVENTO 3 — Tercera edición | C11: Madrid 🇪🇸 | D11: Cree en ti: despierta tu poder interior | E11: 🎯 Objetivo
A12: Oct 2025 | B12: Inicio gestión legal LATAM | C12: Madrid/CDMX | D12: Asesor fiscal México · Estructura operativa | E12: 📋 Planificar
A13: Enero 2026 | B13: EVENTO 4 — Gira LATAM arranca | C13: Ciudad de México 🇲🇽 | D13: Primer evento internacional | E13: 🌎 En ruta
A14: Febrero 2026 | B14: EVENTO 5 | C14: Cancún 🇲🇽 | D14: Segunda parada México | E14: 🌎 En ruta
A15: Febrero 2026 | B15: EVENTO 6 | C15: Mérida 🇲🇽 | D15: Tercera parada México | E15: 🌎 En ruta
... A19: 2027 | B19: Expansión España — Bilbao | C19: Bilbao 🇪🇸 | D19: Norte de España | E19: 🔭 Visión
A22: Leyenda de estados
A23: ⏳ Pendiente
A24: 🎯 Objetivo
A25: 📋 Planificar
A26: 🌎 En ruta
A27: 🔭 Visión
